blnk_py/__init__.py
blnk_py/client.py
blnk_py/config.py
blnk_py/errors.py
blnk_py/http.py
blnk_py/py.typed
blnk_py/types.py
blnk_py/models/balances.py
blnk_py/models/common.py
blnk_py/models/ledgers.py
blnk_py/models/reconciliation.py
blnk_py/models/transactions.py
blnk_py/resources/balances.py
blnk_py/resources/ledgers.py
blnk_py/resources/reconciliation.py
blnk_py/resources/search.py
blnk_py/resources/transactions.py
blnk_py-0.2.0a3.dist-info/METADATA
blnk_py-0.2.0a3.dist-info/WHEEL
blnk_py-0.2.0a3.dist-info/RECORD
