Metadata-Version: 2.4
Name: blnk-py
Version: 0.2.0a3
Summary: Async Python SDK for the Blnk ledger & reconciliation API (typed, Pydantic)
Author-email: Maintainers <maintainers@example.org>
License: MIT
Requires-Python: >=3.9
Requires-Dist: httpx>=0.27.0
Requires-Dist: pydantic<3,>=2.7
Requires-Dist: typing-extensions>=4.9.0
Provides-Extra: dev
Requires-Dist: fastapi; extra == 'dev'
Requires-Dist: mypy; extra == 'dev'
Requires-Dist: pytest; extra == 'dev'
Requires-Dist: pytest-asyncio; extra == 'dev'
Requires-Dist: python-dotenv; extra == 'dev'
Requires-Dist: ruff; extra == 'dev'
Requires-Dist: uvicorn; extra == 'dev'
